{
  "aboutads": [
    {
      "ADSON": true,
      "isgoogle": true,
      "facebookbanner": "85748",
      "facebookinterstitial": "8876876",
      "facebooknative": "867868",
      "disclaimer": "-  This app is made by mahabharatadevlopers. \n-  We do not own any website available in app.\n-   This is not any official application. we are not affiliated by any firm or government.\n-   We do not affiliated with any government entity, services or person.\n-   we don't own any copyrights of images or details used in this app. all the credits goes to their creator. our app doesn't collect any information from users.\n-   we are just providing information that is already available on the internet publicly.\n-   if you have any problem then feel free to contact us at mahabharatadevlopers@gmail.com. \nThank you.",
      "appnextid": "sdgdfhdfhdfhfdh",
      "maxbanner": "8767867",
      "maxinterstitial": "86876876",
      "maxnative": "78678678",
      "maxrewarded": "6786888",
      "interstitialfrequancy": 1,
      "nativefrequancy": 1,
      "googlebanner": "ca-app-pub-3940256099942544/6300978111",
      "googleinterstitial": "ca-app-pub-3940256099942544/1033173712",
      "googlenative": "ca-app-pub-3940256099942544/2247696110"
    }
  ],
  "watches": [
    {
      "Name": "TJKENLLA",
      "Features": {
        "Battery": true,
        "Date": true,
        "Day": true,
        "Steps": true,
        "Weather": true,
        "Pulse": true,
        "Distance": true,
        "Digital": true,
        "24 Hours format": true
      },
      "Developer": "TJKENLLA",
      "giflink": "https://amazfitwatchfaces.com/storage/mi-band-6/img/1651604819_012e8be34d.gif",
      "binlink": "https://harshil258.github.io/apitesting/watch%20faces/TJKENLLA.bin"
    },
    {
      "Name": "tristan0824",
      "Features": {
        "Battery": true,
        "Date": true,
        "Day": true,
        "Steps": false,
        "Weather": true,
        "Pulse": true,
        "Distance": false,
        "Digital": true,
        "24 Hours format": false
      },
      "Developer": "tristan0824",
      "giflink": "https://amazfitwatchfaces.com/storage/mi-band-6/img/1651676449_9eedfebd18.gif",
      "binlink": "https://harshil258.github.io/apitesting/watch%20faces/tristan0824.bin"
    },
    {
      "Name": "aingerun",
      "Features": {
        "Battery": true,
        "Date": true,
        "Day": false,
        "Steps": true,
        "Weather": false,
        "Pulse": false,
        "Distance": false,
        "Digital": true,
        "24 Hours format": false
      },
      "Developer": "aingerun",
      "giflink": "https://amazfitwatchfaces.com/storage/mi-band-6/img/1651736288_52034063aa.png",
      "binlink": "https://harshil258.github.io/apitesting/watch%20faces/aingerun.bin"
    },
    {
      "Name": " BIFAN",
      "Features": {
        "Battery": true,
        "Date": true,
        "Day": false,
        "Steps": true,
        "Weather": true,
        "Pulse": true,
        "Distance": false,
        "Digital": true,
        "24 Hours format": false
      },
      "Developer": " BIFAN",
      "giflink": "https://amazfitwatchfaces.com/storage/mi-band-6/img/1652513218_6f023c87dc.gif",
      "binlink": "https://harshil258.github.io/apitesting/watch%20faces/ BIFAN.bin"
    },
    {
      "Name": "aishbi",
      "Features": {
        "Battery": true,
        "Date": true,
        "Day": true,
        "Steps": true,
        "Weather": true,
        "Pulse": true,
        "Distance": true,
        "Digital": true,
        "24 Hours format": false
      },
      "Developer": "aishbi",
      "giflink": "https://amazfitwatchfaces.com/storage/mi-band-6/img/1652021448_78f152177e.gif",
      "binlink": "https://harshil258.github.io/apitesting/watch%20faces/aishbi.bin"
    },
    {
      "Name": "Nike Modular\n",
      "Features": {
        "Battery": true,
        "Date": true,
        "Day": true,
        "Steps": true,
        "Weather": true,
        "Pulse": true,
        "Distance": true,
        "Digital": true,
        "24 Hours format": false
      },
      "Developer": "Nike Modular\n",
      "giflink": "https://getech2018.github.io/mb5/mb5_1724.gif",
      "binlink": "http://miwatchfaces.com/files/mb5/mb5_1724.bin"
    },
    {
      "Name": "Birba",
      "Features": {
        "Battery": true,
        "Date": true,
        "Day": true,
        "Steps": true,
        "Weather": true,
        "Pulse": true,
        "Distance": true,
        "Digital": true,
        "24 Hours format": false
      },
      "Developer": "Birba",
      "giflink": "https://amazfitwatchfaces.com/storage/mi-band-6/img/1652364905_71d5b713d2.gif",
      "binlink": "https://harshil258.github.io/apitesting/watch%20faces/Birba.bin"
    },
    {
      "Name": "Dartwagner_MB6_Orange",
      "Features": {
        "Battery": true,
        "Date": true,
        "Day": true,
        "Steps": true,
        "Weather": false,
        "Pulse": true,
        "Distance": false,
        "Digital": true,
        "24 Hours format": false
      },
      "Developer": "Dartwagner",
      "giflink": "https://amazfitwatchfaces.com/storage/mi-band-6/img/1654906805_bceb614c3b.gif",
      "binlink": "https://harshil258.github.io/apitesting/watch%20faces/Dartwagner.bin"
    },
    {
      "Name": "Rocket_League_B6",
      "Features": {
        "Battery": true,
        "Date": true,
        "Day": true,
        "Steps": true,
        "Weather": true,
        "Pulse": true,
        "Distance": true,
        "Digital": true,
        "24 Hours format": true
      },
      "Developer": "JerryB86",
      "giflink": "https://amazfitwatchfaces.com/storage/mi-band-6/img/1654810199_d022bef96f.gif",
      "binlink": "https://harshil258.github.io/apitesting/watch%20faces/JerryB86.bin"
    },
    {
      "Name": "Cute_Ice_Bear",
      "Features": {
        "Battery": true,
        "Date": true,
        "Day": false,
        "Steps": true,
        "Weather": true,
        "Pulse": true,
        "Distance": true,
        "Digital": true,
        "24 Hours format": false
      },
      "Developer": "Alonzo",
      "giflink": "https://amazfitwatchfaces.com/storage/mi-band-6/img/1653850949_3600fa1aa7.gif",
      "binlink": "https://harshil258.github.io/apitesting/watch%20faces/Alonzo.bin"
    },
    {
      "Name": "Sunaookami_Shiroko_Blue",
      "Features": {
        "Battery": true,
        "Date": true,
        "Day": false,
        "Steps": true,
        "Weather": true,
        "Pulse": true,
        "Distance": true,
        "Digital": true,
        "24 Hours format": false
      },
      "Developer": "sashikiwa",
      "giflink": "https://amazfitwatchfaces.com/storage/mi-band-6/img/1653185327_3aa2f233fb.gif",
      "binlink": "https://harshil258.github.io/apitesting/watch%20faces/sashikiwa.bin"
    },
    {
      "Name": "Rit_Fut_Scossa",
      "Features": {
        "Battery": true,
        "Date": true,
        "Day": false,
        "Steps": true,
        "Weather": true,
        "Pulse": true,
        "Distance": true,
        "Digital": true,
        "24 Hours format": false
      },
      "Developer": "Birba",
      "giflink": "https://amazfitwatchfaces.com/storage/mi-band-6/img/1652960057_fd93cd9ec1.gif",
      "binlink": "https://harshil258.github.io/apitesting/watch%20faces/Birba.bin"
    },
    {
      "Name": "Akebi's_Sailor",
      "Features": {
        "Battery": true,
        "Date": true,
        "Day": true,
        "Steps": true,
        "Weather": false,
        "Pulse": false,
        "Distance": false,
        "Digital": true,
        "24 Hours format": false
      },
      "Developer": "RayLZ",
      "giflink": "https://amazfitwatchfaces.com/storage/mi-band-6/img/1652756741_480c6a6123.gif",
      "binlink": "https://harshil258.github.io/apitesting/watch%20faces/RayLZ.bin"
    },
    {
      "Name": "Dartwagner_MB6_Red",
      "Features": {
        "Battery": true,
        "Date": true,
        "Day": true,
        "Steps": true,
        "Weather": false,
        "Pulse": false,
        "Distance": false,
        "Digital": true,
        "24 Hours format": false
      },
      "Developer": "Dartwagner",
      "giflink": "https://amazfitwatchfaces.com/storage/mi-band-6/img/1652658230_42fdad798a.gif",
      "binlink": "https://harshil258.github.io/apitesting/watch%20faces/Dart.bin"
    },
    {
      "Name": "Dartwagner_MB6_Red",
      "Features": {
        "Battery": true,
        "Date": true,
        "Day": true,
        "Steps": true,
        "Weather": false,
        "Pulse": false,
        "Distance": false,
        "Digital": true,
        "24 Hours format": false
      },
      "Developer": "Dartwagner",
      "giflink": "https://amazfitwatchfaces.com/storage/mi-band-6/img/1652658230_42fdad798a.gif",
      "binlink": "https://harshil258.github.io/apitesting/watch%20faces/Dart.bin"
    },
    {
      "Name": "Jinjer",
      "Features": {
        "Battery": true,
        "Date": true,
        "Day": true,
        "Steps": true,
        "Weather": true,
        "Pulse": true,
        "Distance": true,
        "Digital": true,
        "24 Hours format": false
      },
      "Developer": "aishbi",
      "giflink": "https://amazfitwatchfaces.com/storage/mi-band-6/img/1652540886_8b6e11913c.gif",
      "binlink": "https://harshil258.github.io/apitesting/watch%20faces/aishbi.bin"
    },
    {
      "Name": "thewanyingtic",
      "Features": {
        "Battery": true,
        "Date": true,
        "Day": true,
        "Steps": true,
        "Weather": true,
        "Pulse": true,
        "Distance": true,
        "Digital": true,
        "24 Hours format": false
      },
      "Developer": "thewanyingtic",
      "giflink": "https://amazfitwatchfaces.com/storage/mi-band-6/img/1652346345_23076b406f.gif",
      "binlink": "https://harshil258.github.io/apitesting/watch%20faces/thewanyingtic.bin"
    },
    {
      "Name": "Material_You_Black",
      "Features": {
        "Battery": true,
        "Date": true,
        "Day": false,
        "Steps": true,
        "Weather": false,
        "Pulse": true,
        "Distance": false,
        "Digital": true,
        "24 Hours format": false
      },
      "Developer": "kKsk",
      "giflink": "https://amazfitwatchfaces.com/storage/mi-band-6/img/1651970704_d55442502e.gif",
      "binlink": "https://harshil258.github.io/apitesting/watch%20faces/kKsk.bin"
    },
    {
      "Name": "Slime_tree",
      "Features": {
        "Battery": true,
        "Date": true,
        "Day": false,
        "Steps": true,
        "Weather": false,
        "Pulse": true,
        "Distance": false,
        "Digital": true,
        "24 Hours format": false
      },
      "Developer": "SmallGoldFish",
      "giflink": "https://amazfitwatchfaces.com/storage/mi-band-6/img/1651949755_3bd17ccf98.gif",
      "binlink": "https://harshil258.github.io/apitesting/watch%20faces/SmallGoldFish.bin"
    },
    {
      "Name": "zsoltee69",
      "Features": {
        "Battery": true,
        "Date": true,
        "Day": false,
        "Steps": true,
        "Weather": false,
        "Pulse": true,
        "Distance": true,
        "Digital": true,
        "24 Hours format": false
      },
      "Developer": "zsoltee69",
      "giflink": "https://amazfitwatchfaces.com/storage/mi-band-6/img/1655356807_391865cf3e.jpg",
      "binlink": "https://harshil258.github.io/apitesting/watch%20faces/zsoltee69.bin"
    },
    {
      "Name": "Dark89",
      "Features": {
        "Battery": true,
        "Date": true,
        "Day": false,
        "Steps": false,
        "Weather": false,
        "Pulse": true,
        "Distance": false,
        "Digital": true,
        "24 Hours format": false
      },
      "Developer": "Darkangel8904",
      "giflink": "https://amazfitwatchfaces.com/storage/mi-band-6/img/1651793996_113916256a.gif",
      "binlink": "https://harshil258.github.io/apitesting/watch%20faces/Darkangel8904.bin"
    },
    {
      "Name": "PHANTASMAGORIA",
      "Features": {
        "Battery": true,
        "Date": true,
        "Day": false,
        "Steps": true,
        "Weather": true,
        "Pulse": true,
        "Distance": true,
        "Digital": true,
        "24 Hours format": true
      },
      "Developer": "smokycat",
      "giflink": "https://amazfitwatchfaces.com/storage/mi-band-6/img/1652696064_716902a636.gif",
      "binlink": "https://harshil258.github.io/apitesting/watch%20faces/smokycat.bin"
    },
    {
      "Name": "Jinjer",
      "Features": {
        "Battery": true,
        "Date": true,
        "Day": false,
        "Steps": true,
        "Weather": false,
        "Pulse": true,
        "Distance": true,
        "Digital": true,
        "24 Hours format": true
      },
      "Developer": "aishbiii",
      "giflink": "https://amazfitwatchfaces.com/storage/mi-band-6/img/1652540886_8b6e11913c.gif",
      "binlink": "https://harshil258.github.io/apitesting/watch%20faces/aishbiii.bin"
    },
    {
      "Name": "amoled3",
      "Features": {
        "Battery": true,
        "Date": true,
        "Day": false,
        "Steps": true,
        "Weather": true,
        "Pulse": true,
        "Distance": true,
        "Digital": true,
        "24 Hours format": true
      },
      "Developer": "amoled3",
      "giflink": "https://amazfitwatchfaces.com/storage/mi-band-6/img/1652017599_0816066c04.gif",
      "binlink": "https://harshil258.github.io/apitesting/watch%20faces/amoled3.bin"
    },
    {
      "Name": "Iga_No_Kabamaru",
      "Features": {
        "Battery": true,
        "Date": true,
        "Day": true,
        "Steps": true,
        "Weather": true,
        "Pulse": true,
        "Distance": true,
        "Digital": true,
        "24 Hours format": true
      },
      "Developer": "JerryB86",
      "giflink": "https://amazfitwatchfaces.com/storage/mi-band-6/img/1652007831_1d5df78b94.gif",
      "binlink": "https://harshil258.github.io/apitesting/watch%20faces/JerryB861.bin"
    },
    {
      "Name": "Sport_Red",
      "Features": {
        "Battery": true,
        "Date": true,
        "Day": true,
        "Steps": true,
        "Weather": false,
        "Pulse": true,
        "Distance": true,
        "Digital": true,
        "24 Hours format": false
      },
      "Developer": "Vadiminho_99",
      "giflink": "https://amazfitwatchfaces.com/storage/mi-band-6/img/1651670662_13db672277.png",
      "binlink": "https://harshil258.github.io/apitesting/watch%20faces/Vadiminho_99.bin"
    },
    {
      "Name": "The_bruh_war",
      "Features": {
        "Battery": true,
        "Date": true,
        "Day": true,
        "Steps": true,
        "Weather": false,
        "Pulse": true,
        "Distance": true,
        "Digital": true,
        "24 Hours format": false
      },
      "Developer": "xuanphucdev",
      "giflink": "https://amazfitwatchfaces.com/storage/mi-band-6/img/1651596857_282bb15101.gif",
      "binlink": "https://harshil258.github.io/apitesting/watch%20faces/xuanphucdev.bin"
    },
    {
      "Name": "Funny_Dog",
      "Features": {
        "Battery": true,
        "Date": true,
        "Day": true,
        "Steps": true,
        "Weather": false,
        "Pulse": true,
        "Distance": true,
        "Digital": true,
        "24 Hours format": false
      },
      "Developer": "xuanphucdev",
      "giflink": "https://amazfitwatchfaces.com/storage/mi-band-6/img/1651582777_4c7509a9fb.gif",
      "binlink": "https://harshil258.github.io/apitesting/watch%20faces/Funny_Dog.bin"
    },
    {
      "Name": "To_Space",
      "Features": {
        "Battery": true,
        "Date": true,
        "Day": false,
        "Steps": true,
        "Weather": false,
        "Pulse": false,
        "Distance": false,
        "Digital": true,
        "24 Hours format": false
      },
      "Developer": "To_Space",
      "giflink": "https://amazfitwatchfaces.com/storage/mi-band-6/img/1651502842_9c63d52e79.gif",
      "binlink": "https://harshil258.github.io/apitesting/watch%20faces/To_Space.bin"
    },
    {
      "Name": "Lane_Ehhsex",
      "Features": {
        "Battery": true,
        "Date": true,
        "Day": false,
        "Steps": true,
        "Weather": false,
        "Pulse": true,
        "Distance": false,
        "Digital": true,
        "24 Hours format": true
      },
      "Developer": "SadFaceMan",
      "giflink": "https://amazfitwatchfaces.com/storage/mi-band-6/img/1650646229_f22c2af868.png",
      "binlink": "https://harshil258.github.io/apitesting/watch%20faces/SadFaceMan.bin"
    }
  ]
}
